markdownify_filter/__init__.py
markdownify_filter/templatetags/__init__.py
markdownify_filter/templatetags/markdownify_filter.py
django_markdownify_filter-0.1.1.dist-info/LICENSE
django_markdownify_filter-0.1.1.dist-info/METADATA
django_markdownify_filter-0.1.1.dist-info/WHEEL
django_markdownify_filter-0.1.1.dist-info/top_level.txt
django_markdownify_filter-0.1.1.dist-info/RECORD
